snapchat_dlp/__init__.py
snapchat_dlp/app.py
snapchat_dlp/cli.py
snapchat_dlp/downloader.py
snapchat_dlp/snapchat_dlp.py
snapchat_dlp/utils.py
snapchat_dlp/version.py
snapchat_dlp-1.5.13.dist-info/AUTHORS.rst
snapchat_dlp-1.5.13.dist-info/LICENSE
snapchat_dlp-1.5.13.dist-info/METADATA
snapchat_dlp-1.5.13.dist-info/WHEEL
snapchat_dlp-1.5.13.dist-info/entry_points.txt
snapchat_dlp-1.5.13.dist-info/top_level.txt
snapchat_dlp-1.5.13.dist-info/RECORD
