Metadata-Version: 2.1
Name: snapchat-dlp
Version: 1.5.13
Summary: An update to snapchat-dlp, a Snapchat Public Stories Downloader.
Home-page: https://github.com/Walmann/snapchat-dlp
Author: Aakash Gajjar
Author-email: skyqutip@gmail.com
Maintainer: Walmann
License: MIT license
Project-URL: Original, https://github.com/skyme5/snapchat-dlp
Project-URL: Source, https://github.com/Walmann/snapchat-dlp
Keywords: snapchat-dlp
Platform: UNKNOWN
Classifier: Development Status :: 5 - Production/Stable
Classifier: Environment :: Console
Classifier: Intended Audience :: Developers
Classifier: Intended Audience :: End Users/Desktop
Classifier: License :: OSI Approved :: MIT License
Classifier: Natural Language :: English
Classifier: Programming Language :: Python :: 3
Classifier: Programming Language :: Python :: 3.5
Classifier: Programming Language :: Python :: 3.6
Classifier: Programming Language :: Python :: 3.7
Classifier: Programming Language :: Python :: 3.8
Classifier: Programming Language :: Python :: 3.9
Classifier: Programming Language :: Python :: 3.10
Requires-Python: >=3.5
Requires-Dist: loguru
Requires-Dist: pyperclip
Requires-Dist: requests
